sfti_net/__init__.py
sfti_net/send.py
sfti_net/watch.py
sfti_net-0.0.1.dist-info/LICENSE
sfti_net-0.0.1.dist-info/METADATA
sfti_net-0.0.1.dist-info/WHEEL
sfti_net-0.0.1.dist-info/entry_points.txt
sfti_net-0.0.1.dist-info/top_level.txt
sfti_net-0.0.1.dist-info/RECORD
