Metadata-Version: 2.1
Name: sfti-net
Version: 0.0.1
Summary: Package to send data in the SFTI Biotechnology Spearhead project
Author: Ben Hong
Author-email: Ben Hong <benjamin.hong476@gmail.com>
Project-URL: Homepage, https://github.com/ben476/pysislab
Project-URL: Bug Tracker, https://github.com/ben476/pysislab/issues
Classifier: Development Status :: 3 - Alpha
Classifier: Intended Audience :: Developers
Classifier: Programming Language :: Python :: 3 :: Only
Classifier: Topic :: Software Development :: Libraries :: Python Modules
Classifier: Topic :: Utilities
Requires-Python: >=3.7
License-File: LICENSE
Requires-Dist: watchfiles
